{
  "李白": {
    "籍贯": "绵州昌隆县（今四川江油）",
    "主要行迹": [
      {"时期": "开元十五年", "地点": "长安"},
      {"时期": "天宝三载", "地点": "扬州"},
      {"时期": "天宝十四载", "地点": "庐山"},
      {"时期": "乾元元年", "地点": "泗州"}
    ]
  },
  "杜甫": {
    "籍贯": "河南巩县（今河南巩义）",
    "主要行迹": [
      {"时期": "开元二十九年", "地点": "长安"},
      {"时期": "天宝十四载", "地点": "长安"},
      {"时期": "乾元元年", "地点": "华州"},
      {"时期": "广德二年", "地点": "奉节"},
      {"时期": "宝应元年", "地点": "成都"}
    ]
  },
  "白居易": {
    "籍贯": "河南新郑",
    "主要行迹": [
      {"时期": "贞元十六年", "地点": "长安"},
      {"时期": "元和十年", "地点": "江州"},
      {"时期": "元和十一年", "地点": "忠州"},
      {"时期": "长庆四年", "地点": "杭州"},
      {"时期": "宝历二年", "地点": "苏州"}
    ]
  },
  "王维": {
    "籍贯": "蒲州濮阳（今山西运城）",
    "主要行迹": [
      {"时期": "开元九年", "地点": "长安"},
      {"时期": "开元二十三年", "地点": "辋川"},
      {"时期": "天宝十三载", "地点": "长安"}
    ]
  },
  "孟浩然": {
    "籍贯": "襄州襄阳（今湖北襄阳）",
    "主要行迹": [
      {"时期": "开元二十年", "地点": "长安"},
      {"时期": "开元二十一年", "地点": "洛阳"},
      {"时期": "天宝元年", "地点": "襄阳"}
    ]
  },
  "岑参": {
    "籍贯": "南京金陵（今江苏南京）",
    "主要行迹": [
      {"时期": "天宝十载", "地点": "长安"},
      {"时期": "天宝十一载", "地点": "龟兹"},
      {"时期": "至德二载", "地点": "长安"}
    ]
  },
  "柳永": {
    "籍贯": "崇安县（今福建武夷山市）",
    "主要行迹": [
      {"时期": "北宋真宗年间", "地点": "开封"},
      {"时期": "天圣年间", "地点": "杭州"},
      {"时期": "景祐年间", "地点": "苏州"}
    ]
  },
  "苏轼": {
    "籍贯": "眉州眉山（今四川眉山）",
    "主要行迹": [
      {"时期": "嘉祐二年", "地点": "开封"},
      {"时期": "元祐三年", "地点": "杭州"},
      {"时期": "元祐七年", "地点": "密州"},
      {"时期": "绍圣三年", "地点": "黄州"},
      {"时期": "建中靖国元年", "地点": "惠州"}
    ]
  },
  "辛弃疾": {
    "籍贯": "济南历城（今山东济南）",
    "主要行迹": [
      {"时期": "绍兴三十一年", "地点": "建康"},
      {"时期": "隆兴元年", "地点": "鄱阳"},
      {"时期": "淳熙十四年", "地点": "上饶"},
      {"时期": "开禧元年", "地点": "铅山"}
    ]
  },
  "李清照": {
    "籍贯": "齐州章丘（今山东济南）",
    "主要行迹": [
      {"时期": "崇宁年间", "地点": "青州"},
      {"时期": "建炎元年", "地点": "南京"},
      {"时期": "建炎四年", "地点": "金华"},
      {"时期": "绍兴五年", "地点": "杭州"}
    ]
  },
  "范仲淹": {
    "籍贯": "苏州吴县（今江苏苏州）",
    "主要行迹": [
      {"时期": "景祐元年", "地点": "邠州"},
      {"时期": "庆历三年", "地点": "延州"},
      {"时期": "庆历五年", "地点": "杭州"},
      {"时期": "庆历六年", "地点": "潍州"}
    ]
  },
  "欧阳修": {
    "籍贯": "庐陵（今江西吉安）",
    "主要行迹": [
      {"时期": "庆历二年", "地点": "洛阳"},
      {"时期": "庆历六年", "地点": "滁州"},
      {"时期": "皇祐元年", "地点": "汝州"},
      {"时期": "嘉祐元年", "地点": "颖州"}
    ]
  },
  "王安石": {
    "籍贯": "临川（今江西抚州）",
    "主要行迹": [
      {"时期": "庆历八年", "地点": "南京"},
      {"时期": "嘉祐六年", "地点": "江宁"},
      {"时期": "熙宁三年", "地点": "汴京"},
      {"时期": "元丰元年", "地点": "金陵"}
    ]
  },
  "陆游": {
    "籍贯": "越州山阴（今浙江绍兴）",
    "主要行迹": [
      {"时期": "淳熙八年", "地点": "成都"},
      {"时期": "淳熙十四年", "地点": "夔州"},
      {"时期": "绍熙三年", "地点": "南郑"},
      {"时期": "嘉泰元年", "地点": "山阴"}
    ]
  },
  "贺铸": {
    "籍贯": "卫州武陟（今河南焦作）",
    "主要行迹": [
      {"时期": "元祐年间", "地点": "开封"},
      {"时期": "绍圣二年", "地点": "太原"},
      {"时期": "元符三年", "地点": "杭州"}
    ]
  },
  "王昌龄": {
    "籍贯": "太原祁县（今山西祁县）",
    "主要行迹": [
      {"时期": "开元二十三年", "地点": "长安"},
      {"时期": "天宝七载", "地点": "江宁"},
      {"时期": "天宝十载", "地点": "岭南"}
    ]
  },
  "李贺": {
    "籍贯": "福昌县昌谷（今河南宜阳）",
    "主要行迹": [
      {"时期": "元和十年", "地点": "长安"},
      {"时期": "元和十一年", "地点": "洛阳"}
    ]
  }
}
